PyOffice/Calculator.py
PyOffice/Suite.py
PyOffice/Word.py
PyOffice/__init__.py
PyOffice-0.2.dist-info/entry_points.txt
PyOffice-0.2.dist-info/WHEEL
PyOffice-0.2.dist-info/METADATA
PyOffice-0.2.dist-info/RECORD
