Metadata-Version: 2.1
Name: PyOffice
Version: 0.2
Summary: Demonstrate docstrings and does nothing really.
Home-page: https://github.com/mynameisvinn/pyoffice
License: UNKNOWN
Author: vincent tang
Author-email: vin.tang@gmail.com
Maintainer: mynameisvinn
Maintainer-email: vin.tang@gmail.com
Requires-Python: >=3.6
